Workbook

Sheet 1. Problemas
A1: Matriz de Vester · TicketFlow
A2: Los diez problemas del mercado de boleteria en Colombia que entran al cruce. Salen del enunciado del Proyecto Integrador, del analisis PESTEL del equipo y del benchmark de Tuboleta, Eventbrite, Ticketmaster y Taquilla Live.
A4: Codigo | B4: Problema | C4: De donde sale
A5: P1 | B5: Desconfianza del comprador en las plataformas de boleteria | C5: Caso SIC vs. Tuboleta; analisis PESTEL (factor legal)
A6: P2 | B6: Precio final oculto hasta el checkout (cargos sorpresa) | C6: Benchmark: cargos por servicio de Eventbrite y Ticketmaster
A7: P3 | B7: Reventa y suplantacion de boletas | C7: Benchmark del sector (Tuboleta, Ticketmaster)
A8: P4 | B8: Sobreventa y descontrol del aforo por gestion manual | C8: Enunciado: Evento.capacidad total de espectadores
A9: P5 | B9: Reembolsos lentos o incumplidos (Ley 2439 de 2024) | C9: Ley 2439 de 2024; analisis PESTEL (factor legal)
A10: P6 | B10: Ausencia de un canal PQRS digital y trazable | C10: Caso SIC (cargo por fallas en PQRS); PESTEL legal
A11: P7 | B11: Organizadores pequenos sin herramientas digitales | C11: Enunciado: perfil Agente; PESTEL (factor tecnologico)
A12: P8 | B12: Caidas de la plataforma en picos de venta | C12: Analisis PESTEL (factor tecnologico)
A13: P9 | B13: Abandono de la compra antes de confirmar | C13: Benchmark: abandono de carrito por cargos sorpresa
A14: P10 | B14: Baja recompra y poca fidelizacion del cliente | C14: Enunciado: campo Cliente.puntos
A16: Escala de causalidad usada en la hoja 2: 0 = no lo causa · 1 = lo causa de forma debil o indirecta · 2 = lo causa de forma media · 3 = lo causa de forma directa y fuerte

Sheet 2. Matriz
A1: El cruce
A2: Cada casilla responde: ¿cuanto causa el problema de la FILA al problema de la COLUMNA? Solo se editan las casillas del cruce (B5:K14). La influencia, la dependencia y los cortes son formulas.
A4: causa ↓ / efecto → | B4: P1 | C4: P2 | D4: P3 | E4: P4 | F4: P5 | G4: P6 | H4: P7 | I4: P8 | J4: P9 | K4: P10 | L4: INFLUENCIA | N4: Cortes de los ejes
A5: P1 | B5: — | C5: 0 | D5: 0 | E5: 0 | F5: 0 | G5: 0 | H5: 0 | I5: 0 | J5: 3 | K5: 3 | L5: =SUM(B5:K5) | N5: Corte en X (influencia) | O5: =MAX(L5:L14)/2
A6: P2 | B6: 3 | C6: — | D6: 0 | E6: 0 | F6: 1 | G6: 0 | H6: 0 | I6: 0 | J6: 3 | K6: 2 | L6: =SUM(B6:K6) | N6: Corte en Y (dependencia) | O6: =MAX(B15:K15)/2
A7: P3 | B7: 3 | C7: 0 | D7: — | E7: 2 | F7: 1 | G7: 1 | H7: 0 | I7: 0 | J7: 1 | K7: 2 | L7: =SUM(B7:K7)
A8: P4 | B8: 3 | C8: 0 | D8: 1 | E8: — | F8: 3 | G8: 2 | H8: 0 | I8: 0 | J8: 1 | K8: 3 | L8: =SUM(B8:K8) | N8: Comprobacion | O8: =IF(SUM(L5:L14)=SUM(B15:K15),"Correcta: las filas y las columnas suman igual","OJO: hay un error de captura")
A9: P5 | B9: 3 | C9: 0 | D9: 0 | E9: 0 | F9: — | G9: 2 | H9: 0 | I9: 0 | J9: 1 | K9: 3 | L9: =SUM(B9:K9)
A10: P6 | B10: 3 | C10: 0 | D10: 0 | E10: 0 | F10: 3 | G10: — | H10: 0 | I10: 0 | J10: 0 | K10: 2 | L10: =SUM(B10:K10) | N10: El corte va en la mitad del rango de cada eje, que es el criterio habitual de la matriz de Vester.
A11: P7 | B11: 2 | C11: 1 | D11: 3 | E11: 3 | F11: 2 | G11: 3 | H11: — | I11: 0 | J11: 2 | K11: 1 | L11: =SUM(B11:K11)
A12: P8 | B12: 2 | C12: 0 | D12: 0 | E12: 2 | F12: 1 | G12: 1 | H12: 0 | I12: — | J12: 3 | K12: 2 | L12: =SUM(B12:K12)
A13: P9 | B13: 0 | C13: 0 | D13: 0 | E13: 0 | F13: 0 | G13: 0 | H13: 1 | I13: 0 | J13: — | K13: 2 | L13: =SUM(B13:K13)
A14: P10 | B14: 0 | C14: 0 | D14: 0 | E14: 0 | F14: 0 | G14: 0 | H14: 1 | I14: 0 | J14: 0 | K14: — | L14: =SUM(B14:K14)
A15: DEPENDENCIA | B15: =SUM(B5:B14) | C15: =SUM(C5:C14) | D15: =SUM(D5:D14) | E15: =SUM(E5:E14) | F15: =SUM(F5:F14) | G15: =SUM(G5:G14) | H15: =SUM(H5:H14) | I15: =SUM(I5:I14) | ... L15: =SUM(L5:L14)

Sheet 3. Clasificacion
A1: Clasificacion por cuadrante
A2: Todo en esta hoja son formulas que leen la hoja 2. El cuadrante se decide comparando la influencia y la dependencia de cada problema contra los cortes.
A4: Codigo | B4: Problema | C4: Influencia | D4: Dependencia | E4: Cuadrante
A5: P1 | B5: ='1. Problemas'!B5 | C5: ='2. Matriz'!L5 | D5: =INDEX('2. Matriz'!$B$15:$K$15,1) | E5: =IF(AND(C5>='2. Matriz'!$O$5,D5>='2. Matriz'!$O$6),"Critico",IF(AND(C5>='2. Matriz'!$O$5,D5<'2. Matriz'!$O$6),"Activo",IF(AND(C5<'2. Matriz'!$O$5,D5>='2. Matriz'!$O$6),"Pasivo","Indiferente")))
A6: P2 | B6: ='1. Problemas'!B6 | C6: ='2. Matriz'!L6 | D6: =INDEX('2. Matriz'!$B$15:$K$15,2) | E6: =IF(AND(C6>='2. Matriz'!$O$5,D6>='2. Matriz'!$O$6),"Critico",IF(AND(C6>='2. Matriz'!$O$5,D6<'2. Matriz'!$O$6),"Activo",IF(AND(C6<'2. Matriz'!$O$5,D6>='2. Matriz'!$O$6),"Pasivo","Indiferente")))
A7: P3 | B7: ='1. Problemas'!B7 | C7: ='2. Matriz'!L7 | D7: =INDEX('2. Matriz'!$B$15:$K$15,3) | E7: =IF(AND(C7>='2. Matriz'!$O$5,D7>='2. Matriz'!$O$6),"Critico",IF(AND(C7>='2. Matriz'!$O$5,D7<'2. Matriz'!$O$6),"Activo",IF(AND(C7<'2. Matriz'!$O$5,D7>='2. Matriz'!$O$6),"Pasivo","Indiferente")))
A8: P4 | B8: ='1. Problemas'!B8 | C8: ='2. Matriz'!L8 | D8: =INDEX('2. Matriz'!$B$15:$K$15,4) | E8: =IF(AND(C8>='2. Matriz'!$O$5,D8>='2. Matriz'!$O$6),"Critico",IF(AND(C8>='2. Matriz'!$O$5,D8<'2. Matriz'!$O$6),"Activo",IF(AND(C8<'2. Matriz'!$O$5,D8>='2. Matriz'!$O$6),"Pasivo","Indiferente")))
A9: P5 | B9: ='1. Problemas'!B9 | C9: ='2. Matriz'!L9 | D9: =INDEX('2. Matriz'!$B$15:$K$15,5) | E9: =IF(AND(C9>='2. Matriz'!$O$5,D9>='2. Matriz'!$O$6),"Critico",IF(AND(C9>='2. Matriz'!$O$5,D9<'2. Matriz'!$O$6),"Activo",IF(AND(C9<'2. Matriz'!$O$5,D9>='2. Matriz'!$O$6),"Pasivo","Indiferente")))
A10: P6 | B10: ='1. Problemas'!B10 | C10: ='2. Matriz'!L10 | D10: =INDEX('2. Matriz'!$B$15:$K$15,6) | E10: =IF(AND(C10>='2. Matriz'!$O$5,D10>='2. Matriz'!$O$6),"Critico",IF(AND(C10>='2. Matriz'!$O$5,D10<'2. Matriz'!$O$6),"Activo",IF(AND(C10<'2. Matriz'!$O$5,D10>='2. Matriz'!$O$6),"Pasivo","Indiferente")))
A11: P7 | B11: ='1. Problemas'!B11 | C11: ='2. Matriz'!L11 | D11: =INDEX('2. Matriz'!$B$15:$K$15,7) | E11: =IF(AND(C11>='2. Matriz'!$O$5,D11>='2. Matriz'!$O$6),"Critico",IF(AND(C11>='2. Matriz'!$O$5,D11<'2. Matriz'!$O$6),"Activo",IF(AND(C11<'2. Matriz'!$O$5,D11>='2. Matriz'!$O$6),"Pasivo","Indiferente")))
A12: P8 | B12: ='1. Problemas'!B12 | C12: ='2. Matriz'!L12 | D12: =INDEX('2. Matriz'!$B$15:$K$15,8) | E12: =IF(AND(C12>='2. Matriz'!$O$5,D12>='2. Matriz'!$O$6),"Critico",IF(AND(C12>='2. Matriz'!$O$5,D12<'2. Matriz'!$O$6),"Activo",IF(AND(C12<'2. Matriz'!$O$5,D12>='2. Matriz'!$O$6),"Pasivo","Indiferente")))
A13: P9 | B13: ='1. Problemas'!B13 | C13: ='2. Matriz'!L13 | D13: =INDEX('2. Matriz'!$B$15:$K$15,9) | E13: =IF(AND(C13>='2. Matriz'!$O$5,D13>='2. Matriz'!$O$6),"Critico",IF(AND(C13>='2. Matriz'!$O$5,D13<'2. Matriz'!$O$6),"Activo",IF(AND(C13<'2. Matriz'!$O$5,D13>='2. Matriz'!$O$6),"Pasivo","Indiferente")))
A14: P10 | B14: ='1. Problemas'!B14 | C14: ='2. Matriz'!L14 | D14: =INDEX('2. Matriz'!$B$15:$K$15,10) | E14: =IF(AND(C14>='2. Matriz'!$O$5,D14>='2. Matriz'!$O$6),"Critico",IF(AND(C14>='2. Matriz'!$O$5,D14<'2. Matriz'!$O$6),"Activo",IF(AND(C14<'2. Matriz'!$O$5,D14>='2. Matriz'!$O$6),"Pasivo","Indiferente")))
A17: Como se lee cada cuadrante
A19: ACTIVO | B19: Causa mucho y casi nadie lo causa. Son las raices del problema: es por aqui por donde hay que atacar.
A20: CRITICO | B20: Causa y es causado a la vez. Es el punto donde el problema se realimenta; si no se resuelve, cualquier mejora aguas arriba se pierde.
A21: PASIVO | B21: Casi pura consecuencia. No se ataca de frente: se arregla resolviendo los activos y los criticos.
A22: INDIFERENTE | B22: Ni causa ni es causado de forma relevante. Baja prioridad, salvo que quede limitrofe con otro cuadrante.

Sheet 4. Plano
A1: Plano de causalidad
A2: Cada problema se ubica segun cuanto causa (eje X) y cuanto lo causan (eje Y). Las cuatro series separan los cuadrantes: si se cambia un valor en la hoja 2, el punto cambia de serie y de color solo.
A29: Datos del grafico (no borrar)
A30: Cod | B30: INF | C30: DEP | D30: Critico X | E30: Critico Y | F30: Activo X | G30: Activo Y | H30: Pasivo X | I30: Pasivo Y | J30: Indif. X | K30: Indif. Y
A31: P1 | B31: ='3. Clasificacion'!C5 | C31: ='3. Clasificacion'!D5 | D31: =IF('3. Clasificacion'!E5="Critico",B31,NA()) | E31: =IF('3. Clasificacion'!E5="Critico",C31,NA()) | F31: =IF('3. Clasificacion'!E5="Activo",B31,NA()) | G31: =IF('3. Clasificacion'!E5="Activo",C31,NA()) | H31: =IF('3. Clasificacion'!E5="Pasivo",B31,NA()) | I31: =IF('3. Clasificacion'!E5="Pasivo",C31,NA()) | J31: =IF('3. Clasificacion'!E5="Indiferente",B31,NA()) | K31: =IF('3. Clasificacion'!E5="Indiferente",C31,NA())
A32: P2 | B32: ='3. Clasificacion'!C6 | C32: ='3. Clasificacion'!D6 | D32: =IF('3. Clasificacion'!E6="Critico",B32,NA()) | E32: =IF('3. Clasificacion'!E6="Critico",C32,NA()) | F32: =IF('3. Clasificacion'!E6="Activo",B32,NA()) | G32: =IF('3. Clasificacion'!E6="Activo",C32,NA()) | H32: =IF('3. Clasificacion'!E6="Pasivo",B32,NA()) | I32: =IF('3. Clasificacion'!E6="Pasivo",C32,NA()) | J32: =IF('3. Clasificacion'!E6="Indiferente",B32,NA()) | K32: =IF('3. Clasificacion'!E6="Indiferente",C32,NA())
A33: P3 | B33: ='3. Clasificacion'!C7 | C33: ='3. Clasificacion'!D7 | D33: =IF('3. Clasificacion'!E7="Critico",B33,NA()) | E33: =IF('3. Clasificacion'!E7="Critico",C33,NA()) | F33: =IF('3. Clasificacion'!E7="Activo",B33,NA()) | G33: =IF('3. Clasificacion'!E7="Activo",C33,NA()) | H33: =IF('3. Clasificacion'!E7="Pasivo",B33,NA()) | I33: =IF('3. Clasificacion'!E7="Pasivo",C33,NA()) | J33: =IF('3. Clasificacion'!E7="Indiferente",B33,NA()) | K33: =IF('3. Clasificacion'!E7="Indiferente",C33,NA())
A34: P4 | B34: ='3. Clasificacion'!C8 | C34: ='3. Clasificacion'!D8 | D34: =IF('3. Clasificacion'!E8="Critico",B34,NA()) | E34: =IF('3. Clasificacion'!E8="Critico",C34,NA()) | F34: =IF('3. Clasificacion'!E8="Activo",B34,NA()) | G34: =IF('3. Clasificacion'!E8="Activo",C34,NA()) | H34: =IF('3. Clasificacion'!E8="Pasivo",B34,NA()) | I34: =IF('3. Clasificacion'!E8="Pasivo",C34,NA()) | J34: =IF('3. Clasificacion'!E8="Indiferente",B34,NA()) | K34: =IF('3. Clasificacion'!E8="Indiferente",C34,NA())
A35: P5 | B35: ='3. Clasificacion'!C9 | C35: ='3. Clasificacion'!D9 | D35: =IF('3. Clasificacion'!E9="Critico",B35,NA()) | E35: =IF('3. Clasificacion'!E9="Critico",C35,NA()) | F35: =IF('3. Clasificacion'!E9="Activo",B35,NA()) | G35: =IF('3. Clasificacion'!E9="Activo",C35,NA()) | H35: =IF('3. Clasificacion'!E9="Pasivo",B35,NA()) | I35: =IF('3. Clasificacion'!E9="Pasivo",C35,NA()) | J35: =IF('3. Clasificacion'!E9="Indiferente",B35,NA()) | K35: =IF('3. Clasificacion'!E9="Indiferente",C35,NA())
A36: P6 | B36: ='3. Clasificacion'!C10 | C36: ='3. Clasificacion'!D10 | D36: =IF('3. Clasificacion'!E10="Critico",B36,NA()) | E36: =IF('3. Clasificacion'!E10="Critico",C36,NA()) | F36: =IF('3. Clasificacion'!E10="Activo",B36,NA()) | G36: =IF('3. Clasificacion'!E10="Activo",C36,NA()) | H36: =IF('3. Clasificacion'!E10="Pasivo",B36,NA()) | I36: =IF('3. Clasificacion'!E10="Pasivo",C36,NA()) | J36: =IF('3. Clasificacion'!E10="Indiferente",B36,NA()) | K36: =IF('3. Clasificacion'!E10="Indiferente",C36,NA())
A37: P7 | B37: ='3. Clasificacion'!C11 | C37: ='3. Clasificacion'!D11 | D37: =IF('3. Clasificacion'!E11="Critico",B37,NA()) | E37: =IF('3. Clasificacion'!E11="Critico",C37,NA()) | F37: =IF('3. Clasificacion'!E11="Activo",B37,NA()) | G37: =IF('3. Clasificacion'!E11="Activo",C37,NA()) | H37: =IF('3. Clasificacion'!E11="Pasivo",B37,NA()) | I37: =IF('3. Clasificacion'!E11="Pasivo",C37,NA()) | J37: =IF('3. Clasificacion'!E11="Indiferente",B37,NA()) | K37: =IF('3. Clasificacion'!E11="Indiferente",C37,NA())
A38: P8 | B38: ='3. Clasificacion'!C12 | C38: ='3. Clasificacion'!D12 | D38: =IF('3. Clasificacion'!E12="Critico",B38,NA()) | E38: =IF('3. Clasificacion'!E12="Critico",C38,NA()) | F38: =IF('3. Clasificacion'!E12="Activo",B38,NA()) | G38: =IF('3. Clasificacion'!E12="Activo",C38,NA()) | H38: =IF('3. Clasificacion'!E12="Pasivo",B38,NA()) | I38: =IF('3. Clasificacion'!E12="Pasivo",C38,NA()) | J38: =IF('3. Clasificacion'!E12="Indiferente",B38,NA()) | K38: =IF('3. Clasificacion'!E12="Indiferente",C38,NA())
A39: P9 | B39: ='3. Clasificacion'!C13 | C39: ='3. Clasificacion'!D13 | D39: =IF('3. Clasificacion'!E13="Critico",B39,NA()) | E39: =IF('3. Clasificacion'!E13="Critico",C39,NA()) | F39: =IF('3. Clasificacion'!E13="Activo",B39,NA()) | G39: =IF('3. Clasificacion'!E13="Activo",C39,NA()) | H39: =IF('3. Clasificacion'!E13="Pasivo",B39,NA()) | I39: =IF('3. Clasificacion'!E13="Pasivo",C39,NA()) | J39: =IF('3. Clasificacion'!E13="Indiferente",B39,NA()) | K39: =IF('3. Clasificacion'!E13="Indiferente",C39,NA())
A40: P10 | B40: ='3. Clasificacion'!C14 | C40: ='3. Clasificacion'!D14 | D40: =IF('3. Clasificacion'!E14="Critico",B40,NA()) | E40: =IF('3. Clasificacion'!E14="Critico",C40,NA()) | F40: =IF('3. Clasificacion'!E14="Activo",B40,NA()) | G40: =IF('3. Clasificacion'!E14="Activo",C40,NA()) | H40: =IF('3. Clasificacion'!E14="Pasivo",B40,NA()) | I40: =IF('3. Clasificacion'!E14="Pasivo",C40,NA()) | J40: =IF('3. Clasificacion'!E14="Indiferente",B40,NA()) | K40: =IF('3. Clasificacion'!E14="Indiferente",C40,NA())
