Workbook

Sheet Instructivo
A1: Manual del Usuario — Matriz PESTEL TicketFlow
A3: PROYECTO: TicketFlow — Sistema web para la gestión de eventos, espectáculos y reservas.
A4: MERCADO ANALIZADO: Colombia (nacional).
A5: REFERENTES DEL SECTOR: Tuboleta, Taquilla Live, Eventbrite, Ticketmaster.
A7: ¿QUÉ ES EL ANÁLISIS PESTEL?
A8: El acrónimo PESTEL agrupa seis factores del macro-entorno que afectan a una empresa: Políticos, Económicos, Sociales, Tecnológicos, Ecológicos/Ambientales y Legales. El objetivo es identificar oportunidades y amenazas externas antes de tomar decisiones estratégicas.
A10: ESTRUCTURA DEL LIBRO:
A11: 1. Hoja 'Áreas': lista de los seis factores evaluados.
A12: 2. Hojas F_Pol, F_Eco, F_Soc, F_Tec, F_Amb, F_Leg: análisis detallado de cada factor con tres aspectos evaluados.
A13: 3. Hoja 'Matriz PESTEL': consolidado de los aspectos con mayor puntuación por factor.
A14: 4. Hoja 'Rel_PESTEL': análisis relativo — peso porcentual de cada factor sobre el total.
A16: CÓMO SE PUNTÚA CADA ASPECTO:
... A43: • Bloomberg Línea / Semana / Portafolio — Sector entretenimiento 2025-2026.

Sheet Áreas
A1: Áreas del Análisis PESTEL
A2: Políticos
A3: Económicos
A4: Sociales
A5: Tecnológicos
A6: Ambientales
A7: Legales

Sheet F_Pol
B1: TicketFlow — Proyecto Integrador 2026-2
B2: FACTOR POLÍTICO
B3: # | C3: Aspectos a evaluar en Factores Político | D3: ¿Cómo puede impactar en TicketFlow? | E3: Importancia | F3: Marco Temporal | G3: Intensidad | H3: Tipo de Tendencia | I3: Puntuación
B4: 1 | C4: Estabilidad política y su impacto en regulaciones de eventos masivos | D4: Un entorno político estable facilita la obtención de permisos y la operación normal de la plataforma; la inestabilidad puede generar cambios normativos abruptos que afecten la programación de eventos. | E4: Importante | F4: Indefinido | G4: Fuerte | H4: Indiferente | I4: =(IF(E4="Sin importancia",1,IF(E4="Poco importante",2,IF(E4="Indiferente",3,IF(E4="Importante",4,IF(E4="Muy importante",5,0)))))*IF(G4="Muy Débil",1,IF(G4="Débil",2,IF(G4="Promedio",3,IF(G4="Fuerte",4,IF(G4="Muy Fuerte",5,0)))))*IF(H4="Mucho Peor",1,IF(H4="Peor",2,IF(H4="Indiferente",3,IF(H4="Mejora",4,IF(H4="Mejora Mucho",5,0)))))) -> 48
B5: 2 | C5: Políticas de fomento a la industria cultural y creativa (Ministerio de Cultura) | D5: Programas de apoyo al sector cultural amplían la oferta de eventos disponibles en la plataforma y generan mayor volumen de reservas. | E5: Muy importante | F5: Indefinido | G5: Fuerte | H5: Mejora | I5: =(IF(E5="Sin importancia",1,IF(E5="Poco importante",2,IF(E5="Indiferente",3,IF(E5="Importante",4,IF(E5="Muy importante",5,0)))))*IF(G5="Muy Débil",1,IF(G5="Débil",2,IF(G5="Promedio",3,IF(G5="Fuerte",4,IF(G5="Muy Fuerte",5,0)))))*IF(H5="Mucho Peor",1,IF(H5="Peor",2,IF(H5="Indiferente",3,IF(H5="Mejora",4,IF(H5="Mejora Mucho",5,0)))))) -> 80
B6: 3 | C6: Regulación gubernamental sobre permisos, aforos y logística de eventos públicos | D6: Regulaciones claras y ágiles habilitan a agentes/operadores a publicar eventos con mayor frecuencia; regulaciones restrictivas limitan la oferta. | E6: Muy importante | F6: Indefinido | G6: Muy Fuerte | H6: Mejora | I6: =(IF(E6="Sin importancia",1,IF(E6="Poco importante",2,IF(E6="Indiferente",3,IF(E6="Importante",4,IF(E6="Muy importante",5,0)))))*IF(G6="Muy Débil",1,IF(G6="Débil",2,IF(G6="Promedio",3,IF(G6="Fuerte",4,IF(G6="Muy Fuerte",5,0)))))*IF(H6="Mucho Peor",1,IF(H6="Peor",2,IF(H6="Indiferente",3,IF(H6="Mejora",4,IF(H6="Mejora Mucho",5,0)))))) -> 100
B7: Puntuación global del factor político | I7: =SUM(I4:I6) -> 228
B9: FUENTES DE INFORMACIÓN
B10: MinCultura Colombia — Programa Nacional de Estímulos: https://www.mincultura.gov.co/
B11: Ministerio del Interior — Permisos para espectáculos públicos: https://www.mininterior.gov.co/

Sheet F_Eco
B1: TicketFlow — Proyecto Integrador 2026-2
B2: FACTOR ECONÓMICO
B3: # | C3: Aspectos a evaluar en Factores Económico | D3: ¿Cómo puede impactar en TicketFlow? | E3: Importancia | F3: Marco Temporal | G3: Intensidad | H3: Tipo de Tendencia | I3: Puntuación
B4: 1 | C4: Crecimiento del mercado de eventos en Colombia (USD 6,7B en 2025 → proyección USD 17,1B en 2035, CAGR 9,9%) | D4: Mercado en fuerte expansión asegura una demanda creciente de plataformas digitales de gestión y reserva de eventos. | E4: Muy importante | F4: Indefinido | G4: Muy Fuerte | H4: Mejora Mucho | I4: =(IF(E4="Sin importancia",1,IF(E4="Poco importante",2,IF(E4="Indiferente",3,IF(E4="Importante",4,IF(E4="Muy importante",5,0)))))*IF(G4="Muy Débil",1,IF(G4="Débil",2,IF(G4="Promedio",3,IF(G4="Fuerte",4,IF(G4="Muy Fuerte",5,0)))))*IF(H4="Mucho Peor",1,IF(H4="Peor",2,IF(H4="Indiferente",3,IF(H4="Mejora",4,IF(H4="Mejora Mucho",5,0)))))) -> 125
B5: 2 | C5: Inflación anual del 6,14% (junio 2026) y desaceleración del gasto de hogares | D5: La pérdida de poder adquisitivo puede reducir la frecuencia de compra de boletas de alto valor y presiona a diferenciarse por precio o beneficios. | E5: Muy importante | F5: Definido | G5: Fuerte | H5: Peor | I5: =(IF(E5="Sin importancia",1,IF(E5="Poco importante",2,IF(E5="Indiferente",3,IF(E5="Importante",4,IF(E5="Muy importante",5,0)))))*IF(G5="Muy Débil",1,IF(G5="Débil",2,IF(G5="Promedio",3,IF(G5="Fuerte",4,IF(G5="Muy Fuerte",5,0)))))*IF(H5="Mucho Peor",1,IF(H5="Peor",2,IF(H5="Indiferente",3,IF(H5="Mejora",4,IF(H5="Mejora Mucho",5,0)))))) -> 40
B6: 3 | C6: Sector Artes, Entretenimiento y Recreación creció 11,5% en 2025 (DANE) — mayor avance sectorial del país | D6: El sector es el motor de crecimiento más dinámico, lo que valida la oportunidad de mercado para una plataforma de ticketing local. | E6: Muy importante | F6: Indefinido | G6: Muy Fuerte | H6: Mejora Mucho | I6: =(IF(E6="Sin importancia",1,IF(E6="Poco importante",2,IF(E6="Indiferente",3,IF(E6="Importante",4,IF(E6="Muy importante",5,0)))))*IF(G6="Muy Débil",1,IF(G6="Débil",2,IF(G6="Promedio",3,IF(G6="Fuerte",4,IF(G6="Muy Fuerte",5,0)))))*IF(H6="Mucho Peor",1,IF(H6="Peor",2,IF(H6="Indiferente",3,IF(H6="Mejora",4,IF(H6="Mejora Mucho",5,0)))))) -> 125
B7: Puntuación global del factor económico | I7: =SUM(I4:I6) -> 290
B9: FUENTES DE INFORMACIÓN
B10: Informes de Expertos — Mercado de Eventos en Colombia 2026-2035: https://www.informesdeexpertos.com/informes/mercado-de-eventos-en-colombia
B11: DANE — Cuentas Trimestrales 2025 (sector Artes/Entretenimiento).
B12: El Espectador — Inflación junio 2026: https://www.elespectador.com/economia/macroeconomia/inflacion-colombia-junio-2026-esto-dicen-los-datos-del-dane/
B13: Bloomberg Línea — Entretenimiento como motor 2024-2026.

Sheet F_Soc
B1: TicketFlow — Proyecto Integrador 2026-2
B2: FACTOR SOCIAL
B3: # | C3: Aspectos a evaluar en Factores Social | D3: ¿Cómo puede impactar en TicketFlow? | E3: Importancia | F3: Marco Temporal | G3: Intensidad | H3: Tipo de Tendencia | I3: Puntuación
B4: 1 | C4: Creciente demanda de experiencias en vivo y consumo experiencial post-pandemia | D4: Los hogares reorientan gasto hacia experiencias (conciertos, cine, ecoturismo), aumentando el volumen potencial de reservas en la plataforma. | E4: Muy importante | F4: Indefinido | G4: Muy Fuerte | H4: Mejora Mucho | I4: =(IF(E4="Sin importancia",1,IF(E4="Poco importante",2,IF(E4="Indiferente",3,IF(E4="Importante",4,IF(E4="Muy importante",5,0)))))*IF(G4="Muy Débil",1,IF(G4="Débil",2,IF(G4="Promedio",3,IF(G4="Fuerte",4,IF(G4="Muy Fuerte",5,0)))))*IF(H4="Mucho Peor",1,IF(H4="Peor",2,IF(H4="Indiferente",3,IF(H4="Mejora",4,IF(H4="Mejora Mucho",5,0)))))) -> 125
B5: 2 | C5: Preferencia de compra digital de boletas en jóvenes y clase media urbana | D5: El público objetivo natural de TicketFlow ya está habituado a comprar y gestionar boletas por canales digitales. | E5: Muy importante | F5: Indefinido | G5: Fuerte | H5: Mejora Mucho | I5: =(IF(E5="Sin importancia",1,IF(E5="Poco importante",2,IF(E5="Indiferente",3,IF(E5="Importante",4,IF(E5="Muy importante",5,0)))))*IF(G5="Muy Débil",1,IF(G5="Débil",2,IF(G5="Promedio",3,IF(G5="Fuerte",4,IF(G5="Muy Fuerte",5,0)))))*IF(H5="Mucho Peor",1,IF(H5="Peor",2,IF(H5="Indiferente",3,IF(H5="Mejora",4,IF(H5="Mejora Mucho",5,0)))))) -> 100
B6: 3 | C6: Ciudades intermedias (Medellín, Barranquilla, Cali) consolidadas como destinos habituales de conciertos y eventos deportivos | D6: Amplía la cobertura geográfica potencial más allá de Bogotá y permite alianzas regionales con agentes/operadores locales. | E6: Importante | F6: Indefinido | G6: Fuerte | H6: Mejora | I6: =(IF(E6="Sin importancia",1,IF(E6="Poco importante",2,IF(E6="Indiferente",3,IF(E6="Importante",4,IF(E6="Muy importante",5,0)))))*IF(G6="Muy Débil",1,IF(G6="Débil",2,IF(G6="Promedio",3,IF(G6="Fuerte",4,IF(G6="Muy Fuerte",5,0)))))*IF(H6="Mucho Peor",1,IF(H6="Peor",2,IF(H6="Indiferente",3,IF(H6="Mejora",4,IF(H6="Mejora Mucho",5,0)))))) -> 64
B7: Puntuación global del factor social | I7: =SUM(I4:I6) -> 289
B9: FUENTES DE INFORMACIÓN
B10: Bloomberg Línea — Entretenimiento sector más dinámico 2024.
B11: Portafolio — Auge del entretenimiento y competencia por medios de pago 2025.
B12: Semana — Conciertos y festivales como motor económico 2024.

Sheet F_Tec
B1: TicketFlow — Proyecto Integrador 2026-2
B2: FACTOR TECNOLÓGICO
B3: # | C3: Aspectos a evaluar en Factores Tecnológico | D3: ¿Cómo puede impactar en TicketFlow? | E3: Importancia | F3: Marco Temporal | G3: Intensidad | H3: Tipo de Tendencia | I3: Puntuación
B4: 1 | C4: Billeteras digitales (Nequi, Daviplata) representan el 29% del valor total de transacciones e-commerce en Colombia | D4: La plataforma debe integrarse desde el inicio con billeteras locales para no perder conversión en el checkout. | E4: Muy importante | F4: Indefinido | G4: Muy Fuerte | H4: Mejora Mucho | I4: =(IF(E4="Sin importancia",1,IF(E4="Poco importante",2,IF(E4="Indiferente",3,IF(E4="Importante",4,IF(E4="Muy importante",5,0)))))*IF(G4="Muy Débil",1,IF(G4="Débil",2,IF(G4="Promedio",3,IF(G4="Fuerte",4,IF(G4="Muy Fuerte",5,0)))))*IF(H4="Mucho Peor",1,IF(H4="Peor",2,IF(H4="Indiferente",3,IF(H4="Mejora",4,IF(H4="Mejora Mucho",5,0)))))) -> 125
B5: 2 | C5: El código QR es el método usado en el 76% de pagos móviles en establecimientos comerciales | D5: El estándar QR es idóneo tanto para el pago como para la validación de boletas en el ingreso al evento — una sola tecnología cubre ambos flujos. | E5: Muy importante | F5: Indefinido | G5: Muy Fuerte | H5: Mejora | I5: =(IF(E5="Sin importancia",1,IF(E5="Poco importante",2,IF(E5="Indiferente",3,IF(E5="Importante",4,IF(E5="Muy importante",5,0)))))*IF(G5="Muy Débil",1,IF(G5="Débil",2,IF(G5="Promedio",3,IF(G5="Fuerte",4,IF(G5="Muy Fuerte",5,0)))))*IF(H5="Mucho Peor",1,IF(H5="Peor",2,IF(H5="Indiferente",3,IF(H5="Mejora",4,IF(H5="Mejora Mucho",5,0)))))) -> 100
B6: 3 | C6: Transferencias A2A (Bre-B) proyectadas al 41% del e-commerce colombiano para 2030 | D6: Preparar la arquitectura de pagos para A2A anticipa el desplazamiento del pago con tarjeta y reduce comisiones para agentes. | E6: Importante | F6: Definido | G6: Fuerte | H6: Mejora Mucho | I6: =(IF(E6="Sin importancia",1,IF(E6="Poco importante",2,IF(E6="Indiferente",3,IF(E6="Importante",4,IF(E6="Muy importante",5,0)))))*IF(G6="Muy Débil",1,IF(G6="Débil",2,IF(G6="Promedio",3,IF(G6="Fuerte",4,IF(G6="Muy Fuerte",5,0)))))*IF(H6="Mucho Peor",1,IF(H6="Peor",2,IF(H6="Indiferente",3,IF(H6="Mejora",4,IF(H6="Mejora Mucho",5,0)))))) -> 80
B7: Puntuación global del factor tecnológico | I7: =SUM(I4:I6) -> 305
B9: FUENTES DE INFORMACIÓN
B10: Portafolio — Global Payments Report 2026 (Worldpay): https://www.portafolio.co/tecnologia/bre-b-y-billeteras-impulsan-el-crecimiento-de-los-pagos-digitales-en-colombia-dice-el-global-payments-report-495647
B11: Pulzo — Nequi, DaviPlata y QR cambian el pago en Colombia.
B12: Infobae — Transferencias A2A cambian compras online 2026.

Sheet F_Amb
B1: TicketFlow — Proyecto Integrador 2026-2
B2: FACTOR AMBIENTAL
B3: # | C3: Aspectos a evaluar en Factores Ambiental | D3: ¿Cómo puede impactar en TicketFlow? | E3: Importancia | F3: Marco Temporal | G3: Intensidad | H3: Tipo de Tendencia | I3: Puntuación
B4: 1 | C4: Reducción de papel gracias a boletas digitales / QR frente a boletería física | D4: La operación digital de TicketFlow ya es intrínsecamente más sostenible que la boletería tradicional; puede comunicarse como valor de marca. | E4: Importante | F4: Indefinido | G4: Promedio | H4: Mejora | I4: =(IF(E4="Sin importancia",1,IF(E4="Poco importante",2,IF(E4="Indiferente",3,IF(E4="Importante",4,IF(E4="Muy importante",5,0)))))*IF(G4="Muy Débil",1,IF(G4="Débil",2,IF(G4="Promedio",3,IF(G4="Fuerte",4,IF(G4="Muy Fuerte",5,0)))))*IF(H4="Mucho Peor",1,IF(H4="Peor",2,IF(H4="Indiferente",3,IF(H4="Mejora",4,IF(H4="Mejora Mucho",5,0)))))) -> 48
B5: 2 | C5: Presión creciente por reducir la huella de carbono de eventos masivos (transporte, iluminación, residuos) | D5: Los organizadores empiezan a solicitar reportes ambientales; a mediano plazo la plataforma podría diferenciarse ofreciéndolos. | E5: Indiferente | F5: Indefinido | G5: Débil | H5: Peor | I5: =(IF(E5="Sin importancia",1,IF(E5="Poco importante",2,IF(E5="Indiferente",3,IF(E5="Importante",4,IF(E5="Muy importante",5,0)))))*IF(G5="Muy Débil",1,IF(G5="Débil",2,IF(G5="Promedio",3,IF(G5="Fuerte",4,IF(G5="Muy Fuerte",5,0)))))*IF(H5="Mucho Peor",1,IF(H5="Peor",2,IF(H5="Indiferente",3,IF(H5="Mejora",4,IF(H5="Mejora Mucho",5,0)))))) -> 12
B6: 3 | C6: Riesgo operativo por eventos climáticos extremos (lluvias, olas de calor) que cancelan actividades al aire libre | D6: Aumenta la tasa de cancelaciones y reembolsos, presionando la operación de PQRS y el flujo de caja. | E6: Importante | F6: Indefinido | G6: Promedio | H6: Peor | I6: =(IF(E6="Sin importancia",1,IF(E6="Poco importante",2,IF(E6="Indiferente",3,IF(E6="Importante",4,IF(E6="Muy importante",5,0)))))*IF(G6="Muy Débil",1,IF(G6="Débil",2,IF(G6="Promedio",3,IF(G6="Fuerte",4,IF(G6="Muy Fuerte",5,0)))))*IF(H6="Mucho Peor",1,IF(H6="Peor",2,IF(H6="Indiferente",3,IF(H6="Mejora",4,IF(H6="Mejora Mucho",5,0)))))) -> 24
B7: Puntuación global del factor ambiental | I7: =SUM(I4:I6) -> 84
B9: FUENTES DE INFORMACIÓN
B10: IDEAM — Reportes climatológicos y de riesgo Colombia 2025-2026.
B11: Bloomberg Línea — Sostenibilidad y eventos masivos en LatAm.

Sheet F_Leg
B1: TicketFlow — Proyecto Integrador 2026-2
B2: FACTOR LEGAL
B3: # | C3: Aspectos a evaluar en Factores Legal | D3: ¿Cómo puede impactar en TicketFlow? | E3: Importancia | F3: Marco Temporal | G3: Intensidad | H3: Tipo de Tendencia | I3: Puntuación
B4: 1 | C4: Ley 2439 de 2024 — Modifica el Estatuto del Consumidor: obliga a reembolsos en e-commerce en 15 días calendario y a canales de PQRS con número de trazabilidad | D4: REQUISITO OBLIGATORIO de arquitectura: el módulo de reembolsos y PQRS debe cumplir los plazos y la trazabilidad desde el primer día. No es opcional. | E4: Muy importante | F4: Definido | G4: Muy Fuerte | H4: Mejora | I4: =(IF(E4="Sin importancia",1,IF(E4="Poco importante",2,IF(E4="Indiferente",3,IF(E4="Importante",4,IF(E4="Muy importante",5,0)))))*IF(G4="Muy Débil",1,IF(G4="Débil",2,IF(G4="Promedio",3,IF(G4="Fuerte",4,IF(G4="Muy Fuerte",5,0)))))*IF(H4="Mucho Peor",1,IF(H4="Peor",2,IF(H4="Indiferente",3,IF(H4="Mejora",4,IF(H4="Mejora Mucho",5,0)))))) -> 100
B5: 2 | C5: Investigación abierta por la SIC contra Tuboleta (2026) por fallas en información al consumidor, derecho de retracto y PQRS | D5: Precedente reciente en el mismo sector: cumplir el Estatuto del Consumidor no es teórico — la autoridad ya sanciona activamente. Riesgo legal si no se cumple. | E5: Muy importante | F5: Indefinido | G5: Muy Fuerte | H5: Peor | I5: =(IF(E5="Sin importancia",1,IF(E5="Poco importante",2,IF(E5="Indiferente",3,IF(E5="Importante",4,IF(E5="Muy importante",5,0)))))*IF(G5="Muy Débil",1,IF(G5="Débil",2,IF(G5="Promedio",3,IF(G5="Fuerte",4,IF(G5="Muy Fuerte",5,0)))))*IF(H5="Mucho Peor",1,IF(H5="Peor",2,IF(H5="Indiferente",3,IF(H5="Mejora",4,IF(H5="Mejora Mucho",5,0)))))) -> 50
B6: 3 | C6: Ley 1581 de 2012 (Habeas Data) — Régimen general de protección de datos personales | D6: El manejo de datos de clientes (identificación, correo, teléfono, pagos) requiere política de tratamiento de datos, autorización explícita y medidas de seguridad. | E6: Muy importante | F6: Indefinido | G6: Fuerte | H6: Indiferente | I6: =(IF(E6="Sin importancia",1,IF(E6="Poco importante",2,IF(E6="Indiferente",3,IF(E6="Importante",4,IF(E6="Muy importante",5,0)))))*IF(G6="Muy Débil",1,IF(G6="Débil",2,IF(G6="Promedio",3,IF(G6="Fuerte",4,IF(G6="Muy Fuerte",5,0)))))*IF(H6="Mucho Peor",1,IF(H6="Peor",2,IF(H6="Indiferente",3,IF(H6="Mejora",4,IF(H6="Mejora Mucho",5,0)))))) -> 60
B7: Puntuación global del factor legal | I7: =SUM(I4:I6) -> 210
B9: FUENTES DE INFORMACIÓN
B10: SIC — Estatuto del Consumidor: https://www.sic.gov.co/estatutos-consumidor
B11: Holland & Knight — Análisis Ley 2439 de 2024: https://www.hklaw.com/en/insights/publications/2025/01/ley-2439-de-2024-modificaciones-al-estatuto-del-consumidor-en-colombia
B12: Infobae — SIC investigación Tuboleta 2026: https://www.infobae.com/colombia/2026/06/04/sic-sanciono-a-operadora-de-tu-boleta-por-problemas-de-los-usuarios-al-momento-de-comprar-boleteria/
B13: Función Pública — Ley 1581 de 2012 (Habeas Data).

Sheet Matriz PESTEL
B1: TicketFlow — Matriz PESTEL Consolidada
B3: Factores Político (P) | D3: Factores Económico (E) | F3: Factores Social (S)
B4: Top 3 Aspectos — Factor Político | C4: =SUM(F_Pol!I4:I6) -> 228 | D4: Top 3 Aspectos — Factor Económico | E4: =SUM(F_Eco!I4:I6) -> 290 | F4: Top 3 Aspectos — Factor Social | G4: =SUM(F_Soc!I4:I6) -> 289
B5: =F_Pol!C4 -> Estabilidad política y su impacto en regulaciones de eventos masivos | C5: =F_Pol!I4 -> 48 | D5: =F_Eco!C4 -> Crecimiento del mercado de eventos en Colombia (USD 6,7B en 2025 → proyección USD 17,1B en 2035, CAGR 9,9%) | E5: =F_Eco!I4 -> 125 | F5: =F_Soc!C4 -> Creciente demanda de experiencias en vivo y consumo experiencial post-pandemia | G5: =F_Soc!I4 -> 125
B6: =F_Pol!C5 -> Políticas de fomento a la industria cultural y creativa (Ministerio de Cultura) | C6: =F_Pol!I5 -> 80 | D6: =F_Eco!C5 -> Inflación anual del 6,14% (junio 2026) y desaceleración del gasto de hogares | E6: =F_Eco!I5 -> 40 | F6: =F_Soc!C5 -> Preferencia de compra digital de boletas en jóvenes y clase media urbana | G6: =F_Soc!I5 -> 100
B7: =F_Pol!C6 -> Regulación gubernamental sobre permisos, aforos y logística de eventos públicos | C7: =F_Pol!I6 -> 100 | D7: =F_Eco!C6 -> Sector Artes, Entretenimiento y Recreación creció 11,5% en 2025 (DANE) — mayor avance sectorial del país | E7: =F_Eco!I6 -> 125 | F7: =F_Soc!C6 -> Ciudades intermedias (Medellín, Barranquilla, Cali) consolidadas como destinos habituales de conciertos y eventos deportivos | G7: =F_Soc!I6 -> 64
B9: Factores Tecnológico (T) | D9: Factores Ambiental (A) | F9: Factores Legal (L)
B10: Top 3 Aspectos — Factor Tecnológico | C10: =SUM(F_Tec!I4:I6) -> 305 | D10: Top 3 Aspectos — Factor Ambiental | E10: =SUM(F_Amb!I4:I6) -> 84 | F10: Top 3 Aspectos — Factor Legal | G10: =SUM(F_Leg!I4:I6) -> 210
B11: =F_Tec!C4 -> Billeteras digitales (Nequi, Daviplata) representan el 29% del valor total de transacciones e-commerce en Colombia | C11: =F_Tec!I4 -> 125 | D11: =F_Amb!C4 -> Reducción de papel gracias a boletas digitales / QR frente a boletería física | E11: =F_Amb!I4 -> 48 | F11: =F_Leg!C4 -> Ley 2439 de 2024 — Modifica el Estatuto del Consumidor: obliga a reembolsos en e-commerce en 15 días calendario y a canales de PQRS con número de trazabilidad | G11: =F_Leg!I4 -> 100
B12: =F_Tec!C5 -> El código QR es el método usado en el 76% de pagos móviles en establecimientos comerciales | C12: =F_Tec!I5 -> 100 | D12: =F_Amb!C5 -> Presión creciente por reducir la huella de carbono de eventos masivos (transporte, iluminación, residuos) | E12: =F_Amb!I5 -> 12 | F12: =F_Leg!C5 -> Investigación abierta por la SIC contra Tuboleta (2026) por fallas en información al consumidor, derecho de retracto y PQRS | G12: =F_Leg!I5 -> 50
B13: =F_Tec!C6 -> Transferencias A2A (Bre-B) proyectadas al 41% del e-commerce colombiano para 2030 | C13: =F_Tec!I6 -> 80 | D13: =F_Amb!C6 -> Riesgo operativo por eventos climáticos extremos (lluvias, olas de calor) que cancelan actividades al aire libre | E13: =F_Amb!I6 -> 24 | F13: =F_Leg!C6 -> Ley 1581 de 2012 (Habeas Data) — Régimen general de protección de datos personales | G13: =F_Leg!I6 -> 60
B15: PUNTUACIÓN GLOBAL PESTEL — TicketFlow | G15: =SUM(F_Pol!I4:I6)+SUM(F_Eco!I4:I6)+SUM(F_Soc!I4:I6)+SUM(F_Tec!I4:I6)+SUM(F_Amb!I4:I6)+SUM(F_Leg!I4:I6) -> 1406

Sheet Rel_PESTEL
B1: TicketFlow — Análisis Relativo PESTEL
B3: Factor | C3: Peso Relativo (%) | D3: Puntuación Total
B4: Políticos | C4: =SUM(F_Pol!I4:I6)/(SUM(F_Pol!I4:I6)+SUM(F_Eco!I4:I6)+SUM(F_Soc!I4:I6)+SUM(F_Tec!I4:I6)+SUM(F_Amb!I4:I6)+SUM(F_Leg!I4:I6)) -> 0.16216216 | D4: =SUM(F_Pol!I4:I6) -> 228
B5: Económicos | C5: =SUM(F_Eco!I4:I6)/(SUM(F_Pol!I4:I6)+SUM(F_Eco!I4:I6)+SUM(F_Soc!I4:I6)+SUM(F_Tec!I4:I6)+SUM(F_Amb!I4:I6)+SUM(F_Leg!I4:I6)) -> 0.20625889 | D5: =SUM(F_Eco!I4:I6) -> 290
B6: Sociales | C6: =SUM(F_Soc!I4:I6)/(SUM(F_Pol!I4:I6)+SUM(F_Eco!I4:I6)+SUM(F_Soc!I4:I6)+SUM(F_Tec!I4:I6)+SUM(F_Amb!I4:I6)+SUM(F_Leg!I4:I6)) -> 0.20554765 | D6: =SUM(F_Soc!I4:I6) -> 289
B7: Tecnológicos | C7: =SUM(F_Tec!I4:I6)/(SUM(F_Pol!I4:I6)+SUM(F_Eco!I4:I6)+SUM(F_Soc!I4:I6)+SUM(F_Tec!I4:I6)+SUM(F_Amb!I4:I6)+SUM(F_Leg!I4:I6)) -> 0.21692745 | D7: =SUM(F_Tec!I4:I6) -> 305
B8: Ambientales | C8: =SUM(F_Amb!I4:I6)/(SUM(F_Pol!I4:I6)+SUM(F_Eco!I4:I6)+SUM(F_Soc!I4:I6)+SUM(F_Tec!I4:I6)+SUM(F_Amb!I4:I6)+SUM(F_Leg!I4:I6)) -> 0.059743954 | D8: =SUM(F_Amb!I4:I6) -> 84
B9: Legales | C9: =SUM(F_Leg!I4:I6)/(SUM(F_Pol!I4:I6)+SUM(F_Eco!I4:I6)+SUM(F_Soc!I4:I6)+SUM(F_Tec!I4:I6)+SUM(F_Amb!I4:I6)+SUM(F_Leg!I4:I6)) -> 0.14935989 | D9: =SUM(F_Leg!I4:I6) -> 210
B10: TOTAL | C10: =SUM(C4:C9) -> 1 | D10: =SUM(D4:D9) -> 1406
B13: INTERPRETACIÓN ESTRATÉGICA
B14: 1. El sector de entretenimiento es el motor económico más dinámico de Colombia (creció 11,5% en 2025 según DANE) y el mercado de eventos se proyecta triplicar su tamaño para 2035. Oportunidad de mercado sólida.
B15: 2. Los factores Tecnológico y Económico presentan el mayor puntaje positivo — la adopción de billeteras digitales (Nequi/QR/A2A) y el crecimiento del mercado son las principales oportunidades a capitalizar.
B16: 3. El factor Legal es la amenaza más crítica: la Ley 2439/2024 y el precedente SIC vs. Tuboleta obligan a que PQRS, derecho de retracto y transparencia de precios sean requisitos innegociables desde el sprint 1.
B17: 4. El factor Ambiental tiene el menor peso, pero incluye un riesgo operativo relevante (cancelaciones por clima) que debe considerarse en la política de reembolsos.
B18: 5. La inflación y la desaceleración del gasto de hogares (factor Económico) es una amenaza a monitorear — puede afectar el ticket promedio de las reservas.
